proteas_lib/__init__.py
proteas_lib/control.py
proteas_lib/vision.py
proteas_lib-1.0.0.dist-info/LICENSE
proteas_lib-1.0.0.dist-info/METADATA
proteas_lib-1.0.0.dist-info/WHEEL
proteas_lib-1.0.0.dist-info/top_level.txt
proteas_lib-1.0.0.dist-info/RECORD
