Metadata-Version: 2.1
Name: proteas-lib
Version: 1.0.0
Summary: A Rasperry Pi robot library for educators.
Home-page: https://github.com/eellak/gsoc2019-diyrobot
Author: Christos Chronis
Author-email: hronis@hotmail.com
License: UNKNOWN
Keywords: Robot,STEM,Educational robot,3D Printed Robot
Platform: UNKNOWN
Classifier: Programming Language :: Python :: 3
Classifier: License :: OSI Approved :: MIT License
Classifier: Operating System :: OS Independent
Requires-Dist: netifaces
Requires-Dist: mpu6050-raspberrypi
Requires-Dist: Pillow
Requires-Dist: matplotlib
